nfse/__init__.py
nfse/api_client.py
nfse/config.py
nfse/emissor.py
nfse/models.py
nfse/signer.py
nfse/xml_builder.py
nfse_nacional-0.1.0.dist-info/licenses/LICENSE
nfse_nacional-0.1.0.dist-info/METADATA
nfse_nacional-0.1.0.dist-info/WHEEL
nfse_nacional-0.1.0.dist-info/top_level.txt
nfse_nacional-0.1.0.dist-info/RECORD
