Metadata-Version: 2.4
Name: nfse-nacional
Version: 0.1.0
Summary: SDK Python para integração com a API de emissão de Notas Fiscais de Serviço (NFSe) da Nota Nacional
Author-email: Mupi Systems <contato@mupisystems.com.br>
License: MIT
Project-URL: Homepage, https://github.com/mupisystems/nfse_nacional
Project-URL: Documentation, https://github.com/mupisystems/nfse_nacional
Project-URL: Repository, https://github.com/mupisystems/nfse_nacional
Project-URL: Issues, https://github.com/mupisystems/nfse_nacional/issues
Keywords: nfse,nota-fiscal,servico,api,brasil,fiscal
Classifier: Development Status :: 4 - Beta
Classifier: Intended Audience :: Developers
Classifier: License :: OSI Approved :: MIT License
Classifier: Programming Language :: Python :: 3
Classifier: Programming Language :: Python :: 3.8
Classifier: Programming Language :: Python :: 3.9
Classifier: Programming Language :: Python :: 3.10
Classifier: Programming Language :: Python :: 3.11
Classifier: Programming Language :: Python :: 3.12
Classifier: Topic :: Office/Business :: Financial :: Accounting
Classifier: Topic :: Software Development :: Libraries :: Python Modules
Requires-Python: >=3.8
License-File: LICENSE
Requires-Dist: certifi>=2025.11.12
Requires-Dist: cffi>=2.0.0
Requires-Dist: charset-normalizer>=3.4.4
Requires-Dist: cryptography>=46.0.3
Requires-Dist: elementpath>=5.0.4
Requires-Dist: idna>=3.11
Requires-Dist: lxml>=6.0.2
Requires-Dist: python-dateutil>=2.9.0
Requires-Dist: python-dotenv>=1.2.1
Requires-Dist: requests>=2.32.5
Requires-Dist: requests_pkcs12>=1.27
Requires-Dist: signxml>=4.2.0
Requires-Dist: urllib3>=2.6.2
Requires-Dist: xmlschema>=4.2.0
Provides-Extra: dev
Requires-Dist: pytest>=7.0.0; extra == "dev"
Requires-Dist: pytest-cov>=4.0.0; extra == "dev"
Requires-Dist: ruff>=0.1.0; extra == "dev"
Requires-Dist: coverage>=7.13.0; extra == "dev"
Dynamic: license-file
